asta/__init__.py
asta/_array.py
asta/_internal.py
asta/_tensor.py
asta/_tftensor.py
asta/array.py
asta/classes.py
asta/config.py
asta/constants.py
asta/decorators.py
asta/dims.py
asta/display.py
asta/origins.py
asta/parser.py
asta/placeholder.py
asta/scalar.py
asta/shapes.py
asta/substitution.py
asta/switchboard.py
asta/symbols.py
asta/tensor.py
asta/tftensor.py
asta/unusable.py
asta/utils.py
asta/warning.py
asta/defaults/astarc
asta-0.0.7.dist-info/LICENSE
asta-0.0.7.dist-info/METADATA
asta-0.0.7.dist-info/WHEEL
asta-0.0.7.dist-info/top_level.txt
asta-0.0.7.dist-info/RECORD
