Metadata-Version: 2.1
Name: asta
Version: 0.0.7
Summary: Shape annotations for homogeneous numpy arrays and pytorch/tensorflow tensors.
Home-page: UNKNOWN
Author: Brendan Whitaker
License: GPLv3
Platform: UNKNOWN
Classifier: Development Status :: 3 - Alpha
Classifier: Intended Audience :: Developers
Classifier: Intended Audience :: Education
Classifier: Intended Audience :: Science/Research
Classifier: Topic :: Utilities
Classifier: License :: OSI Approved :: BSD License
Classifier: Topic :: Scientific/Engineering
Classifier: Programming Language :: Python :: 3.7
Requires-Python: >=3.7.0
Requires-Dist: toml
Requires-Dist: numpy
Requires-Dist: sympy
Requires-Dist: oxentiel
